{
    "label": "DecisionCapacityAssessment",
    "id": "8",
    "mainTitle": "AVALIAÇÃO DA CAPACIDADE DE DECISÃO",
    "mainButtonLabel": "Baixe um modelo de diretiva",
    "explain": "Para avaliar a capacidade de tomar decisões, são necessários alguns elementos: o paciente conseguir comunicar à equipe sua preferência por um tratamento ou outro; entender os riscos, benefícios e alternativas, inclusive o risco de morte; apreciar a informação, aplicando-a considerando aspectos pessoais de sua vontade e história de vida; deve conseguir utilizar um pensamento racional para chegar a sua escolha. A opinião do paciente pode diferir da equipe clínica, mas com decisões dentro de uma trajetória lógica."
  }
  